{
    "name": "Taunt",
    "description": "",
    
    "effect": null,
    "actions":
    [
        {
            "name": "Bring It On!",
            "cost": 4,
            "diceSpace": true,
            "description": "Put the hero dice here until the end of the round. While it is there, adversaries on adjacent spaces cannot attack other heroes unless they also have similar effect."
        }
    ],
    "affects": [ "bladeborn" ],
    "additionalEffect": "adversaries nearby which should move towards the nearest hero will move towards you even if you are not the closest hero.",
    
    "categories": [ "support" ],
    "set": "twilight-god",
    "type": "skill"
}