{
    "name": "Evasive",
    
    "description": "You weave like smoke around enemies' blades, easily evading even the most masterful strikes.",
    
    "effect": "Before making a save roll, roll a dice. If the result is higher than the attack roll, you dodge aside and the attack has no effect.",
    "affects": [ "swift" ],
    "additionalEffect": "you will also dodge if you roll the same as the attack roll.",
    
    "categories": [ "armour" ],
    "set": "silver-tower",
    "type": "skill"
}